odoo/addons/ssi_payment_order/README.rst
odoo/addons/ssi_payment_order/__init__.py
odoo/addons/ssi_payment_order/__manifest__.py
odoo/addons/ssi_payment_order/menu.xml
odoo/addons/ssi_payment_order/data/approval_template_data.xml
odoo/addons/ssi_payment_order/data/base_automation_data.xml
odoo/addons/ssi_payment_order/data/ir_actions_server_data.xml
odoo/addons/ssi_payment_order/data/ir_sequence_data.xml
odoo/addons/ssi_payment_order/data/policy_template_data.xml
odoo/addons/ssi_payment_order/data/sequence_template_data.xml
odoo/addons/ssi_payment_order/demo/account_account_demo.xml
odoo/addons/ssi_payment_order/demo/account_journal_demo.xml
odoo/addons/ssi_payment_order/demo/payment_order_type_demo.xml
odoo/addons/ssi_payment_order/demo/payment_request_type_demo.xml
odoo/addons/ssi_payment_order/demo/res_bank_demo.xml
odoo/addons/ssi_payment_order/demo/res_partner_bank_demo.xml
odoo/addons/ssi_payment_order/models/__init__.py
odoo/addons/ssi_payment_order/models/account_bank_statement_line.py
odoo/addons/ssi_payment_order/models/account_move.py
odoo/addons/ssi_payment_order/models/account_move_line.py
odoo/addons/ssi_payment_order/models/batch_payment_request.py
odoo/addons/ssi_payment_order/models/payment_order.py
odoo/addons/ssi_payment_order/models/payment_order_type.py
odoo/addons/ssi_payment_order/models/payment_request.py
odoo/addons/ssi_payment_order/models/payment_request_type.py
odoo/addons/ssi_payment_order/security/ir.model.access.csv
odoo/addons/ssi_payment_order/security/ir_module_category_data.xml
odoo/addons/ssi_payment_order/security/ir_rule_data.xml
odoo/addons/ssi_payment_order/security/res_group_data.xml
odoo/addons/ssi_payment_order/static/description/icon.png
odoo/addons/ssi_payment_order/views/account_bank_statement_views.xml
odoo/addons/ssi_payment_order/views/account_move_views.xml
odoo/addons/ssi_payment_order/views/batch_payment_request_views.xml
odoo/addons/ssi_payment_order/views/payment_order_type_views.xml
odoo14_addon_ssi_payment_order-14.0.1.5.0.dist-info/METADATA
odoo14_addon_ssi_payment_order-14.0.1.5.0.dist-info/WHEEL
odoo14_addon_ssi_payment_order-14.0.1.5.0.dist-info/top_level.txt
odoo14_addon_ssi_payment_order-14.0.1.5.0.dist-info/RECORD
