Metadata-Version: 2.1
Name: odoo14-addon-ssi-payment-order
Version: 14.0.1.5.0
Summary: Payment Order
Home-page: https://simetri-sinergi.id
Author: PT. Simetri Sinergi Indonesia, OpenSynergy Indonesia
License: AGPL-3
Platform: UNKNOWN
Classifier: Programming Language :: Python
Classifier: Framework :: Odoo
Classifier: Framework :: Odoo :: 14.0
Classifier: License :: OSI Approved :: GNU Affero General Public License v3
Requires-Python: >=3.6
Requires-Dist: odoo14-addon-ssi-account-account-m2o-configurator-mixin
Requires-Dist: odoo14-addon-ssi-account-journal-m2o-configurator-mixin
Requires-Dist: odoo14-addon-ssi-account-move-line-day-overdue
Requires-Dist: odoo14-addon-ssi-financial-accounting
Requires-Dist: odoo14-addon-ssi-m2o-configurator-mixin
Requires-Dist: odoo14-addon-ssi-master-data-mixin
Requires-Dist: odoo14-addon-ssi-res-currency-m2o-configurator-mixin
Requires-Dist: odoo14-addon-ssi-res-partner-bank-m2o-configurator-mixin
Requires-Dist: odoo14-addon-ssi-res-partner-m2o-configurator-mixin
Requires-Dist: odoo14-addon-ssi-transaction-cancel-mixin
Requires-Dist: odoo14-addon-ssi-transaction-confirm-mixin
Requires-Dist: odoo14-addon-ssi-transaction-date-duration-mixin
Requires-Dist: odoo14-addon-ssi-transaction-done-mixin
Requires-Dist: odoo14-addon-ssi-transaction-open-mixin
Requires-Dist: odoo <14.1dev,>=14.0a
